pyNSID/__init__.py
pyNSID/__version__.py
pyNSID/io/__init__.py
pyNSID/io/hdf_io.py
pyNSID/io/hdf_utils.py
pyNSID-0.0.7.2.dist-info/LICENSE
pyNSID-0.0.7.2.dist-info/METADATA
pyNSID-0.0.7.2.dist-info/WHEEL
pyNSID-0.0.7.2.dist-info/top_level.txt
pyNSID-0.0.7.2.dist-info/RECORD
